{
    "chapters": [
        {
            "code": "01",
            "title": "Unit 1  Can you play the guitar?"
        },
        {
            "code": "02",
            "title": "Unit 2　What timedo you go toschool?"
        },
        {
            "code": "03",
            "title": "Unit 3  How do you get to school?"
        },
        {
            "code": "04",
            "title": "Unit 4  Don’t eatin class."
        },
        {
            "code": "05",
            "title": "Unit 5  Why do you"
        },
        {
            "code": "06",
            "title": "Unit 6  I'm watching TV."
        },
        {
            "code": "07",
            "title": "Unit 7  It's raining!"
        },
        {
            "code": "08",
            "title": "Unit 8  Is there a post office near here?"
        },
        {
            "code": "09",
            "title": "Unit 9  What does he look like?"
        },
        {
            "code": "10",
            "title": "Unit 10　I'd like some noodles."
        },
        {
            "code": "11",
            "title": "Unit 11　How was your school trip?"
        },
        {
            "code": "12",
            "title": "Unit 12　What did you do last weekend?"
        },
        {
            "code": "13",
            "title": "Notes on the Text"
        },
        {
            "code": "14",
            "title": "Tapescripts"
        },
        {
            "code": "15",
            "title": "Pronunciation"
        },
        {
            "code": "16",
            "title": "Grammar"
        },
        {
            "code": "17",
            "title": "Words and Expressions in Each Unit"
        },
        {
            "code": "18",
            "title": "Vocabulary Index"
        },
        {
            "code": "19",
            "title": "Name List"
        },
        {
            "code": "20",
            "title": "Irregular Verbs"
        }
    ],
    "code": "cz_yy_bbb_0702",
    "cover": "http://dzkbw.com/books/rjb/yingyu/xc7x/Cover.jpg",
    "subject": "英语",
    "title": "七年级 下册",
    "version": "部编版"
}
