{
    "chapters": [
        {
            "children": [
                {
                    "code": "01-01",
                    "title": "第一节　自然灾害及其影响"
                },
                {
                    "code": "01-02",
                    "title": "新建章节"
                },
                {
                    "code": "01-03",
                    "title": "第三节　人类活动对自然灾害的影响"
                }
            ],
            "code": "01",
            "title": "第一章 自然灾害与人类活动"
        },
        {
            "children": [
                {
                    "code": "02-01",
                    "title": "第一节　中国自然灾害的特点"
                },
                {
                    "code": "02-02",
                    "title": "第二节　中国的地质灾害"
                },
                {
                    "code": "02-03",
                    "title": "第三节　中国的水文灾害"
                },
                {
                    "code": "02-04",
                    "title": "第四节　中国的气象灾害"
                },
                {
                    "code": "02-05",
                    "title": "第五节　中国的生物灾害"
                }
            ],
            "code": "02",
            "title": "第二章 中国的自然灾害"
        },
        {
            "children": [
                {
                    "code": "03-01",
                    "title": "第一节　自然灾害的监测与防御"
                },
                {
                    "code": "03-02",
                    "title": "第二节　自然灾害的求援与求助"
                },
                {
                    "code": "03-03",
                    "title": "第三节　自然灾害中的自救与互救"
                }
            ],
            "code": "03",
            "title": "第三章 防灾与减灾"
        }
    ],
    "code": "gz_dl_rjb_xx05",
    "cover": "http://dzkbw.com/books/rjb/dili/xgxx5/Cover.jpg",
    "subject": "地理",
    "title": "选修5",
    "version": "人教版"
}
