{
    "chapters": [
        {
            "code": "01",
            "title": "Unit 1  Nex Zealand"
        },
        {
            "code": "02",
            "title": "Unit 2  Detective stories"
        },
        {
            "code": "03",
            "title": "Unit 3  Finding the correct perspective"
        },
        {
            "code": "04",
            "title": "Unit 4  Legends of ancient Greece"
        },
        {
            "code": "05",
            "title": "Unit 5  Launching your career"
        }
    ],
    "code": "gz_yy_rjb_xx11",
    "cover": "http://dzkbw.com/books/rjb/yingyu/xgxx11/Cover.jpg",
    "subject": "英语",
    "title": "选修11",
    "version": "人教版"
}
