{
    "kps": [
        {
            "children": [
                {
                    "code": "XX-LS-01-01",
                    "title": "古代中国的政治制度"
                },
                {
                    "code": "XX-LS-01-02",
                    "title": "古代中国经济的基本结构与特点"
                },
                {
                    "code": "XX-LS-01-03",
                    "title": "中国传统文化主流思想的演变"
                },
                {
                    "code": "XX-LS-01-04",
                    "title": "古代中国的科学技术与文学艺术"
                },
                {
                    "code": "XX-LS-01-05",
                    "title": "古代希腊罗马的政治制度"
                },
                {
                    "code": "XX-LS-01-06",
                    "title": "西方人文主义精神的起源"
                }
            ],
            "code": "XX-LS-01",
            "title": "古代史"
        },
        {
            "children": [
                {
                    "code": "XX-LS-02-01",
                    "title": "西方人文主义精神的发展"
                },
                {
                    "code": "XX-LS-02-02",
                    "title": "\n资本主义世界市场的形成和发展"
                },
                {
                    "code": "XX-LS-02-03",
                    "title": "\n欧美资产阶级代议制的确立与发展"
                },
                {
                    "code": "XX-LS-02-04",
                    "title": "从科学社会主义理论到社会主义制度建立"
                },
                {
                    "code": "XX-LS-02-05",
                    "title": "\n近代科学革命与技术革命"
                },
                {
                    "code": "XX-LS-02-06",
                    "title": "\n19世纪的世界文学艺术"
                },
                {
                    "code": "XX-LS-02-07",
                    "title": "近代中国反侵略、求民主革命"
                },
                {
                    "code": "XX-LS-02-08",
                    "title": "近代中国经济结构的变动与资本主义的曲折发展"
                },
                {
                    "code": "XX-LS-02-09",
                    "title": "近代中国的思想解放潮流"
                },
                {
                    "code": "XX-LS-02-10",
                    "title": "新潮冲击下的社会生活"
                }
            ],
            "code": "XX-LS-02",
            "title": "近代史"
        },
        {
            "children": [
                {
                    "code": "XX-LS-03-01",
                    "title": "\n苏（俄）联的社会主义建设"
                },
                {
                    "code": "XX-LS-03-02",
                    "title": "罗斯福新政和世界资本主义经济政策的调整"
                },
                {
                    "code": "XX-LS-03-03",
                    "title": "第二次世界大战后世界政治格局的演变"
                },
                {
                    "code": "XX-LS-03-04",
                    "title": "第二次世界大战后世界经济的全球化趋势"
                },
                {
                    "code": "XX-LS-03-05",
                    "title": "\n现代科学技术"
                },
                {
                    "code": "XX-LS-03-06",
                    "title": "19世纪以来的世界文学艺术"
                },
                {
                    "code": "XX-LS-03-07",
                    "title": "现代中国的政治建设与祖国统一"
                },
                {
                    "code": "XX-LS-03-08",
                    "title": "中国特色社会主义建设的道路"
                },
                {
                    "code": "XX-LS-03-09",
                    "title": "\n现代中国的对外关系"
                },
                {
                    "code": "XX-LS-03-10",
                    "title": "中国近现代社会生活的变迁"
                },
                {
                    "code": "XX-LS-03-11",
                    "title": "20世纪以来中国重大思想理论发展"
                },
                {
                    "code": "XX-LS-03-12",
                    "title": "20世纪以来中国重大思想理论发展"
                },
                {
                    "code": "XX-LS-03-13",
                    "title": "现代中国的科技，教育与文学艺术"
                },
                {
                    "code": "XX-LS-03-14",
                    "title": "现代中国科技发展的主要成就"
                }
            ],
            "code": "XX-LS-03",
            "title": "现代史"
        },
        {
            "children": [
                {
                    "code": "XX-LS-04-01",
                    "title": "历史上重大改革回眸"
                },
                {
                    "code": "XX-LS-04-02",
                    "title": "\n近代社会的民主思想与实践"
                },
                {
                    "code": "XX-LS-04-03",
                    "title": "世界文化遗产荟萃"
                },
                {
                    "code": "XX-LS-04-04",
                    "title": "20世纪的战争与和平"
                },
                {
                    "code": "XX-LS-04-05",
                    "title": "中外历史人物评说"
                },
                {
                    "code": "XX-LS-04-06",
                    "title": "探索历史的奥秘"
                }
            ],
            "code": "XX-LS-04",
            "title": "其他重要知识点"
        }
    ],
    "subject": "历史",
    "subjectCode": "XX-LS"
}
